{
  "BaseMap": [
    {
      "visual_id": "basemap_illustration",
      "type": "blank",
      "iconSvg": "<svg width='100%' height='100%' xmlns=\"http://www.w3.org/2000/svg\"><defs><linearGradient id=\"skyToDesert\" x1='0%' y1='0%' x2='100%' y2='100%'><stop offset=\"0%\" style=\"stop-color:#87CEEB;stop-opacity:1\" /><stop offset=\"100%\" style=\"stop-color:#EDC9AF;stop-opacity:1\" /></linearGradient></defs><rect width=\"100%\" height=\"100%\" fill=\"url(#skyToDesert)\" /></svg>"
    }
  ],
  "Point": [
    {
      "visual_id": "point_vis_1",
      "iconSvg": "<svg width=\"32\" height=\"32\" viewBox=\"0 0 32 32\" xmlns=\"http://www.w3.org/2000/svg\"><circle cx=\"16\" cy=\"16\" r=\"14\" fill=\"#FFD700\" stroke=\"#FFA500\" stroke-width=\"2\"/><rect x=\"12\" y=\"10\" width=\"8\" height=\"6\" fill=\"#E6C8B9\" rx=\"1\"/><rect x=\"14\" y=\"16\" width=\"4\" height=\"2\" fill=\"#E6C8B9\"/><rect x=\"13\" y=\"18\" width=\"6\" height=\"1\" fill=\"#E6C8B9\"/><rect x=\"14\" y=\"20\" width=\"4\" height=\"1\" fill=\"#E6C8B9\"/></svg>"
    },
    {
      "visual_id": "point_vis_2",
      "iconSvg": "<svg width=\"24\" height=\"24\" viewBox=\"0 0 24 24\" xmlns=\"http://www.w3.org/2000/svg\"><path d=\"M12 2L15.09 8.26L22 9.27L17 14.14L18.18 21.02L12 17.77L5.82 21.02L7 14.14L2 9.27L8.91 8.26L12 2Z\" fill=\"#8BAA4F\"/><circle cx=\"12\" cy=\"10\" r=\"2\" fill=\"#4CAF50\"/></svg>"
    }
  ],
  "Area": [
    {
      "visual_id": "area_vis_1",
      "backgroundColor": "#FFE0B2",
      "borderColor": "#FFA07A",
      "borderWidth": 1,
      "opacity": 0.8
    }
  ],
  "Route": [
    {
      "visual_id": "route_vis_1",
      "color": "#000000",
      "width": 6,
      "style": "navigationCurve"
    },
    {
      "visual_id": "route_vis_2",
      "color": "#FF0000",
      "width": 4,
      "style": "straightLine"
    }
  ],
  "Label": [
    {
      "visual_id": "label_vis_1",
      "template": "<div style=\"font-size: 14px; font-weight: bold; color: #000000; white-space: nowrap;\">{properties.name}</div>"
    },
    {
      "visual_id": "label_vis_2",
      "template": "<div style=\"font-size: 14px; font-weight: bold; color: #000000; white-space: nowrap;\">{properties.name}</div>"
    },
    {
      "visual_id": "label_vis_3",
      "template": "<div style=\"font-size: 14px; font-weight: bold; color: #000000; white-space: nowrap;\">{properties.name}</div>"
    },
    {
      "visual_id": "label_vis_4",
      "template": "<div style=\"font-size: 14px; font-weight: bold; color: #000000; white-space: nowrap;\">{properties.name}</div>"
    },
    {
      "visual_id": "label_vis_5",
      "template": "<div style=\"font-size: 14px; font-weight: bold; color: #000000; white-space: nowrap;\">{properties.name}</div>"
    },
    {
      "visual_id": "label_vis_6",
      "template": "<div style=\"font-size: 14px; font-weight: bold; color: #000000; white-space: nowrap;\">{properties.name}</div>"
    },
    {
      "visual_id": "label_vis_7",
      "template": "<div style=\"font-size: 14px; font-weight: bold; color: #000000; white-space: nowrap;\">{properties.name}</div>"
    },
    {
      "visual_id": "label_vis_8",
      "template": "<div style=\"font-size: 14px; font-weight: bold; color: #000000; white-space: nowrap;\">{properties.name}</div>"
    },
    {
      "visual_id": "label_vis_9",
      "template": "<div style=\"font-size: 14px; font-weight: bold; color: #000000; white-space: nowrap;\">{properties.name}</div>"
    },
    {
      "visual_id": "label_vis_10",
      "template": "<div style=\"font-size: 14px; font-weight: bold; color: #000000; white-space: nowrap;\">{properties.name}</div>"
    },
    {
      "visual_id": "label_vis_11",
      "template": "<div style=\"font-size: 14px; font-weight: bold; color: #000000; white-space: nowrap;\">{properties.name}</div>"
    },
    {
      "visual_id": "label_vis_12",
      "template": "<div style=\"font-size: 14px; font-weight: bold; color: #000000; white-space: nowrap;\">{properties.name}</div>"
    },
    {
      "visual_id": "label_vis_13",
      "template": "<div style=\"font-size: 14px; font-weight: bold; color: #000000; white-space: nowrap;\">{properties.name}</div>"
    },
    {
      "visual_id": "label_vis_14",
      "template": "<div style=\"font-size: 14px; font-weight: bold; color: #000000; white-space: nowrap;\">{properties.name}</div>"
    },
    {
      "visual_id": "label_vis_15",
      "template": "<div style=\"font-size: 14px; font-weight: bold; color: #000000; white-space: nowrap;\">{properties.name}</div>"
    }
  ],
  "Card": [
    {
      "visual_id": "card_vis_1",
      "template": "<div style=\"background-color: #FFE0B2; border: 1px solid #FFA07A; border-radius: 8px; padding: 10px; margin: 5px; box-shadow: 0 2px 5px rgba(0,0,0,0.1); font-family: 'Microsoft YaHei'; font-size: 14px; line-height: 1.5; color: #333333;\">\n  <strong>{properties.name}：</strong>\n  {properties.description}\n</div>"
    },
    {
      "visual_id": "card_vis_2",
      "template": "<div style=\"background-color: #FFE0B2; border: 1px solid #FFA07A; border-radius: 8px; padding: 10px; margin: 5px; box-shadow: 0 2px 5px rgba(0,0,0,0.1); font-family: 'Microsoft YaHei'; font-size: 14px; line-height: 1.5; color: #333333;\">\n  <strong>{properties.name}：</strong>\n  {properties.description}\n</div>"
    },
    {
      "visual_id": "card_vis_3",
      "template": "<div style=\"background-color: #FFE0B2; border: 1px solid #FFA07A; border-radius: 8px; padding: 10px; margin: 5px; box-shadow: 0 2px 5px rgba(0,0,0,0.1); font-family: 'Microsoft YaHei'; font-size: 14px; line-height: 1.5; color: #333333;\">\n  <strong>{properties.name}：</strong>\n  {properties.description}\n</div>"
    },
    {
      "visual_id": "card_vis_4",
      "template": "<div style=\"background-color: #FFE0B2; border: 1px solid #FFA07A; border-radius: 8px; padding: 10px; margin: 5px; box-shadow: 0 2px 5px rgba(0,0,0,0.1); font-family: 'Microsoft YaHei'; font-size: 14px; line-height: 1.5; color: #333333;\">\n  <strong>{properties.name}：</strong>\n  {properties.description}\n</div>"
    },
    {
      "visual_id": "card_vis_5",
      "template": "<div style=\"background-color: #FFE0B2; border: 1px solid #FFA07A; border-radius: 8px; padding: 10px; margin: 5px; box-shadow: 0 2px 5px rgba(0,0,0,0.1); font-family: 'Microsoft YaHei'; font-size: 14px; line-height: 1.5; color: #333333;\">\n  <strong>{properties.name}：</strong>\n  {properties.description}\n</div>"
    },
    {
      "visual_id": "card_vis_6",
      "template": "<div style=\"background-color: #FFE0B2; border: 1px solid #FFA07A; border-radius: 8px; padding: 10px; margin: 5px; box-shadow: 0 2px 5px rgba(0,0,0,0.1); font-family: 'Microsoft YaHei'; font-size: 14px; line-height: 1.5; color: #333333;\">\n  <strong>{properties.name}：</strong>\n  {properties.description}\n</div>"
    },
    {
      "visual_id": "card_vis_7",
      "template": "<div style=\"background-color: #FFE0B2; border: 1px solid #FFA07A; border-radius: 8px; padding: 10px; margin: 5px; box-shadow: 0 2px 5px rgba(0,0,0,0.1); font-family: 'Microsoft YaHei'; font-size: 14px; line-height: 1.5; color: #333333;\">\n  <strong>{properties.name}：</strong>\n  {properties.description}\n</div>"
    },
    {
      "visual_id": "card_vis_8",
      "template": "<div style=\"background-color: #FFE0B2; border: 1px solid #FFA07A; border-radius: 8px; padding: 10px; margin: 5px; box-shadow: 0 2px 5px rgba(0,0,0,0.1); font-family: 'Microsoft YaHei'; font-size: 14px; line-height: 1.5; color: #333333;\">\n  <strong>{properties.name}：</strong>\n  {properties.description}\n</div>"
    },
    {
      "visual_id": "card_vis_9",
      "template": "<div style=\"background-color: #FFE0B2; border: 1px solid #FFA07A; border-radius: 8px; padding: 10px; margin: 5px; box-shadow: 0 2px 5px rgba(0,0,0,0.1); font-family: 'Microsoft YaHei'; font-size: 14px; line-height: 1.5; color: #333333;\">\n  <strong>{properties.name}：</strong>\n  {properties.description}\n</div>"
    }
  ],
  "Edge": [
    {
      "visual_id": "edge_vis_1",
      "anchored_from": "card_vis_2",
      "anchored_to": "point_vis_2",
      "color": "#FF0000",
      "type": "straight"
    },
    {
      "visual_id": "edge_vis_2",
      "anchored_from": "card_vis_3",
      "anchored_to": "point_vis_2",
      "color": "#FF0000",
      "type": "straight"
    },
    {
      "visual_id": "edge_vis_3",
      "anchored_from": "card_vis_4",
      "anchored_to": "point_vis_2",
      "color": "#FF0000",
      "type": "straight"
    },
    {
      "visual_id": "edge_vis_4",
      "anchored_from": "card_vis_5",
      "anchored_to": "point_vis_1",
      "color": "#FF0000",
      "type": "straight"
    },
    {
      "visual_id": "edge_vis_5",
      "anchored_from": "card_vis_6",
      "anchored_to": "point_vis_2",
      "color": "#FF0000",
      "type": "straight"
    },
    {
      "visual_id": "edge_vis_6",
      "anchored_from": "card_vis_7",
      "anchored_to": "point_vis_2",
      "color": "#FF0000",
      "type": "straight"
    },
    {
      "visual_id": "edge_vis_7",
      "anchored_from": "card_vis_8",
      "anchored_to": "point_vis_2",
      "color": "#FF0000",
      "type": "straight"
    },
    {
      "visual_id": "edge_vis_8",
      "anchored_from": "card_vis_9",
      "anchored_to": "point_vis_2",
      "color": "#FF0000",
      "type": "straight"
    }
  ],
  "Global": [
    {
      "visual_id": "global_vis_1",
      "template": "<div style=\"position: absolute; top: 20px; left: 50%; transform: translateX(-50%); font-size: 48px; font-weight: bold; color: #000000; text-align: center; background-color: #FFB347; padding: 10px 20px; border-radius: 8px; z-index: 100; box-shadow: 0 4px 10px rgba(0,0,0,0.2);\">{global_properties[0].title}</div>"
    },
    {
      "visual_id": "global_vis_2",
      "template": "<div style=\"position: absolute; top: 80px; left: 50%; transform: translateX(-50%); font-size: 20px; font-weight: bold; color: #FFFFFF; text-align: center; background-color: #FFA500; padding: 10px 20px; border-radius: 8px; z-index: 100; box-shadow: 0 4px 10px rgba(0,0,0,0.2);\">{global_properties[1].title}</div>"
    }
  ]
}